installlib/__init__.py
installlib/__main__.py
installlib/flow.py
installlib/tasks.py
installlib/utils.py
installlib-0.3.0.dist-info/LICENSE
installlib-0.3.0.dist-info/METADATA
installlib-0.3.0.dist-info/WHEEL
installlib-0.3.0.dist-info/top_level.txt
installlib-0.3.0.dist-info/RECORD
