Metadata-Version: 2.2
Name: installlib
Version: 0.3.0
Summary: Installlib is a small library which helps orchestrating arbitrary scripted tasks.
Author-email: Chen Kasirer <kasirer@arch.ethz.ch>
License: MIT License
Project-URL: Homepage, https://github.com/gramaziokohler/installlib
Project-URL: Repository, https://github.com/gramaziokohler/installlib
Classifier: Development Status :: 4 - Beta
Classifier: Topic :: Scientific/Engineering
Classifier: Programming Language :: Python
Classifier: Programming Language :: Python :: 3
Classifier: Programming Language :: Python :: 3.9
Classifier: Programming Language :: Python :: 3.10
Classifier: Programming Language :: Python :: 3.11
Requires-Python: >=3.9
License-File: LICENSE
Requires-Dist: progress
Provides-Extra: dev
Requires-Dist: pytest-mock; extra == "dev"
Requires-Dist: attrs>=17.4; extra == "dev"
Requires-Dist: bump-my-version; extra == "dev"
Requires-Dist: ruff; extra == "dev"
Requires-Dist: twine; extra == "dev"
Requires-Dist: wheel; extra == "dev"
Requires-Dist: invoke; extra == "dev"
Requires-Dist: sphinx; extra == "dev"
Requires-Dist: build; extra == "dev"
